aiperf/__init__.py
aiperf/__main__.py
aiperf/cli.py
aiperf/cli_runner.py
aiperf/cli_utils.py
aiperf/module_loader.py
aiperf/common/__init__.py
aiperf/common/aiperf_logger.py
aiperf/common/base_comms.py
aiperf/common/base_component_service.py
aiperf/common/base_service.py
aiperf/common/bootstrap.py
aiperf/common/constants.py
aiperf/common/decorators.py
aiperf/common/environment.py
aiperf/common/exceptions.py
aiperf/common/factories.py
aiperf/common/growable_array.py
aiperf/common/hooks.py
aiperf/common/logging.py
aiperf/common/metric_utils.py
aiperf/common/protocols.py
aiperf/common/random_generator.py
aiperf/common/session_id_generator.py
aiperf/common/tokenizer.py
aiperf/common/types.py
aiperf/common/utils.py
aiperf/common/config/__init__.py
aiperf/common/config/audio_config.py
aiperf/common/config/base_config.py
aiperf/common/config/cli_parameter.py
aiperf/common/config/config_defaults.py
aiperf/common/config/config_validators.py
aiperf/common/config/conversation_config.py
aiperf/common/config/endpoint_config.py
aiperf/common/config/groups.py
aiperf/common/config/image_config.py
aiperf/common/config/input_config.py
aiperf/common/config/loader.py
aiperf/common/config/loadgen_config.py
aiperf/common/config/output_config.py
aiperf/common/config/prompt_config.py
aiperf/common/config/rankings_config.py
aiperf/common/config/service_config.py
aiperf/common/config/tokenizer_config.py
aiperf/common/config/user_config.py
aiperf/common/config/video_config.py
aiperf/common/config/worker_config.py
aiperf/common/config/zmq_config.py
aiperf/common/enums/__init__.py
aiperf/common/enums/base_enums.py
aiperf/common/enums/command_enums.py
aiperf/common/enums/communication_enums.py
aiperf/common/enums/data_exporter_enums.py
aiperf/common/enums/dataset_enums.py
aiperf/common/enums/endpoints_enums.py
aiperf/common/enums/logging_enums.py
aiperf/common/enums/media_enums.py
aiperf/common/enums/message_enums.py
aiperf/common/enums/metric_enums.py
aiperf/common/enums/model_enums.py
aiperf-0.4.0.dist-info/METADATA
aiperf-0.4.0.dist-info/WHEEL
aiperf-0.4.0.dist-info/entry_points.txt
aiperf-0.4.0.dist-info/licenses/ATTRIBUTIONS.md
aiperf-0.4.0.dist-info/licenses/LICENSE
aiperf-0.4.0.dist-info/RECORD
