Metadata-Version: 2.4
Name: aiperf
Version: 0.4.0
Summary: AIPerf is a package for performance testing of AI models
Author-email: "NVIDIA Inc." <sw-dl-dynamo@nvidia.com>
License: Apache-2.0
License-File: ATTRIBUTIONS.md
License-File: LICENSE
Requires-Python: >=3.10
Requires-Dist: aiofiles~=24.1.0
Requires-Dist: aiohttp~=3.13.3
Requires-Dist: cyclopts<5,>=4
Requires-Dist: dash-bootstrap-components~=1.6.0
Requires-Dist: dash~=2.18.0
Requires-Dist: ffmpeg-python~=0.2.0
Requires-Dist: jinja2~=3.1.5
Requires-Dist: jmespath~=1.0.1
Requires-Dist: kaleido~=1.2.0
Requires-Dist: matplotlib~=3.9.0
Requires-Dist: numpy~=1.26.4
Requires-Dist: orjson~=3.10.18
Requires-Dist: pandas~=2.3.3
Requires-Dist: pillow~=11.1.0
Requires-Dist: plotly~=6.4.0
Requires-Dist: prometheus-client~=0.23.1
Requires-Dist: psutil~=7.0.0
Requires-Dist: pyarrow>=18.0.0
Requires-Dist: pydantic-settings<3.0.0,>=2.10.0
Requires-Dist: pydantic<3.0.0,>=2.10.0
Requires-Dist: pyzmq~=26.4.0
Requires-Dist: rich~=14.1.0
Requires-Dist: ruamel-yaml~=0.18.12
Requires-Dist: seaborn~=0.13.2
Requires-Dist: setproctitle~=1.3.6
Requires-Dist: soundfile~=0.13.1
Requires-Dist: textual~=5.3.0
Requires-Dist: tqdm>=4.67.1
Requires-Dist: transformers>=4.57.3
Requires-Dist: uvloop~=0.21.0; platform_system != 'Windows'
Provides-Extra: dev
Requires-Dist: black>=25.1.0; extra == 'dev'
Requires-Dist: httpx>=0.27.0; extra == 'dev'
Requires-Dist: mkinit>=1.1.0; extra == 'dev'
Requires-Dist: pre-commit>=4.2.0; extra == 'dev'
Requires-Dist: pytest-asyncio; extra == 'dev'
Requires-Dist: pytest-cov; extra == 'dev'
Requires-Dist: pytest-xdist>=3.8.0; extra == 'dev'
Requires-Dist: pytest>=7.0.0; extra == 'dev'
Requires-Dist: ruff>=0.0.0; extra == 'dev'
Requires-Dist: scipy>=1.13.0; extra == 'dev'
